pdf_to_markdown_llm/__init__.py
pdf_to_markdown_llm/config.py
pdf_to_markdown_llm/logger.py
pdf_to_markdown_llm/logging_config.yaml
pdf_to_markdown_llm/main/cli.py
pdf_to_markdown_llm/model/conversion.py
pdf_to_markdown_llm/model/process_results.py
pdf_to_markdown_llm/service/analyze_files.py
pdf_to_markdown_llm/service/cleanup.py
pdf_to_markdown_llm/service/conversion_support.py
pdf_to_markdown_llm/service/docling_text_conversion.py
pdf_to_markdown_llm/service/gemini_pdf_to_text.py
pdf_to_markdown_llm/service/ollama_text_conversion.py
pdf_to_markdown_llm/service/openai_pdf_to_text.py
pdf_to_markdown_llm-0.1.14.dist-info/licenses/LICENSE
pdf_to_markdown_llm-0.1.14.dist-info/METADATA
pdf_to_markdown_llm-0.1.14.dist-info/WHEEL
pdf_to_markdown_llm-0.1.14.dist-info/RECORD
