Metadata-Version: 2.4
Name: pdf-to-markdown-llm
Version: 0.1.14
Summary: This project contains a command line tool to convert PDF to markdown. It uses image conversion and a LLM to convert the images to markdown.
License-File: LICENSE
Author: Gil Fernandes
Author-email: gil.fernandes@onepointltd.com
Requires-Python: >=3.12,<3.14
Classifier: Programming Language :: Python :: 3
Classifier: Programming Language :: Python :: 3.12
Classifier: Programming Language :: Python :: 3.13
Requires-Dist: click (>=8.1.8,<9.0.0)
Requires-Dist: docling (>=2.70.0)
Requires-Dist: google-generativeai (>=0.8.4,<0.9.0)
Requires-Dist: openai (>=1.76.0,<2.0.0)
Requires-Dist: pdf2image (>=1.17.0,<2.0.0)
Requires-Dist: plum-dispatch (>=1.7.4)
Requires-Dist: pypdf2 (>=3.0.1)
Requires-Dist: python-dotenv (>=1.0.1,<2.0.0)
Requires-Dist: pyyaml (>=6.0.2,<7.0.0)
Requires-Dist: spire-doc (>=13.3.8)
